[
    {
        "title": "day1",
        "urlId": "day1",
        "duration": "",
        "description": "",
        "type": "audio",
        "baseUrl": "https://filedn.com/lSDwSYSe19tRDg0YsJqniij/App_Sitting/1-2020_day5_Zoom/"
    },
    {
        "title": "day2",
        "urlId": "day2",
        "duration": "",
        "description": "",
        "type": "audio",
        "baseUrl": "https://filedn.com/lSDwSYSe19tRDg0YsJqniij/App_Sitting/1-2020_day5_Zoom/"
    },
    {
        "title": "day3",
        "urlId": "day3",
        "duration": "",
        "description": "",
        "type": "audio",
        "baseUrl": "https://filedn.com/lSDwSYSe19tRDg0YsJqniij/App_Sitting/1-2020_day5_Zoom/"
    },
    {
        "title": "day4",
        "urlId": "day4",
        "duration": "",
        "description": "",
        "type": "audio",
        "baseUrl": "https://filedn.com/lSDwSYSe19tRDg0YsJqniij/App_Sitting/1-2020_day5_Zoom/"
    },
    {
        "title": "day5",
        "urlId": "day5",
        "duration": "",
        "description": "",
        "type": "audio",
        "baseUrl": "https://filedn.com/lSDwSYSe19tRDg0YsJqniij/App_Sitting/1-2020_day5_Zoom/"
    }
]